netrun/auth/__init__.py
netrun/auth/config.py
netrun/auth/dependencies.py
netrun/auth/exceptions.py
netrun/auth/jwt.py
netrun/auth/middleware.py
netrun/auth/middleware_casbin.py
netrun/auth/password.py
netrun/auth/py.typed
netrun/auth/rbac.py
netrun/auth/rbac_casbin.py
netrun/auth/types.py
netrun/auth/core/exceptions.py
netrun/auth/integrations/__init__.py
netrun/auth/integrations/azure_ad.py
netrun/auth/integrations/azure_ad_b2c.py
netrun/auth/integrations/oauth.py
netrun/auth/models/__init__.py
netrun/auth/models/rbac_model.conf
netrun/auth/models/rbac_model_tenant.conf
netrun_auth/__init__.py
netrun_auth/config.py
netrun_auth/dependencies.py
netrun_auth/exceptions.py
netrun_auth/jwt.py
netrun_auth/middleware.py
netrun_auth/middleware_casbin.py
netrun_auth/password.py
netrun_auth/rbac.py
netrun_auth/rbac_casbin.py
netrun_auth/types.py
netrun_auth/core/exceptions.py
netrun_auth/integrations/__init__.py
netrun_auth/integrations/azure_ad.py
netrun_auth/integrations/azure_ad_b2c.py
netrun_auth/integrations/oauth.py
netrun_auth/models/__init__.py
netrun_auth/models/rbac_model.conf
netrun_auth/models/rbac_model_tenant.conf
netrun_auth-2.0.0.dist-info/METADATA
netrun_auth-2.0.0.dist-info/WHEEL
netrun_auth-2.0.0.dist-info/licenses/LICENSE
netrun_auth-2.0.0.dist-info/RECORD
