Metadata-Version: 2.4
Name: netrun-auth
Version: 2.0.0
Summary: Unified authentication library for Netrun Systems portfolio - Service #59
Project-URL: Homepage, https://netrunsystems.com
Project-URL: Documentation, https://docs.netrunsystems.com/auth
Project-URL: Repository, https://github.com/netrunsystems/netrun-auth
Project-URL: Issues, https://github.com/netrunsystems/netrun-auth/issues
Project-URL: Changelog, https://github.com/netrunsystems/netrun-auth/blob/main/CHANGELOG.md
Author-email: Daniel Garza <daniel@netrunsystems.com>
License: MIT
License-File: LICENSE
Keywords: authentication,azure-ad,azure-ad-b2c,casbin,fastapi,jwt,mfa,oauth,rbac,security,social-login
Classifier: Development Status :: 5 - Production/Stable
Classifier: Framework :: FastAPI
Classifier: Framework :: Pydantic
Classifier: Framework :: Pydantic :: 2
Classifier: Intended Audience :: Developers
Classifier: License :: OSI Approved :: MIT License
Classifier: Programming Language :: Python :: 3
Classifier: Programming Language :: Python :: 3.10
Classifier: Programming Language :: Python :: 3.11
Classifier: Programming Language :: Python :: 3.12
Classifier: Topic :: Security
Classifier: Topic :: Security :: Cryptography
Classifier: Topic :: Software Development :: Libraries :: Python Modules
Requires-Python: >=3.10
Requires-Dist: casbin>=1.36.0
Requires-Dist: cryptography>=41.0.0
Requires-Dist: netrun-core>=1.0.0
Requires-Dist: pwdlib[argon2]>=0.2.0
Requires-Dist: pydantic-settings>=2.1.0
Requires-Dist: pydantic>=2.5.0
Requires-Dist: pyjwt[crypto]>=2.8.0
Requires-Dist: redis>=5.0.0
Provides-Extra: all
Requires-Dist: authlib>=1.3.0; extra == 'all'
Requires-Dist: azure-identity>=1.15.0; extra == 'all'
Requires-Dist: azure-keyvault-secrets>=4.8.0; extra == 'all'
Requires-Dist: casbin-async-sqlalchemy-adapter>=1.0.0; extra == 'all'
Requires-Dist: casbin-redis-adapter>=1.0.0; extra == 'all'
Requires-Dist: fastapi>=0.109.0; extra == 'all'
Requires-Dist: httpx>=0.26.0; extra == 'all'
Requires-Dist: msal>=1.26.0; extra == 'all'
Requires-Dist: netrun-logging>=2.0.0; extra == 'all'
Requires-Dist: pyjwt[crypto]>=2.8.0; extra == 'all'
Requires-Dist: starlette>=0.36.0; extra == 'all'
Provides-Extra: azure
Requires-Dist: azure-identity>=1.15.0; extra == 'azure'
Requires-Dist: azure-keyvault-secrets>=4.8.0; extra == 'azure'
Requires-Dist: msal>=1.26.0; extra == 'azure'
Provides-Extra: b2c
Requires-Dist: httpx>=0.26.0; extra == 'b2c'
Requires-Dist: msal>=1.26.0; extra == 'b2c'
Requires-Dist: pyjwt[crypto]>=2.8.0; extra == 'b2c'
Provides-Extra: casbin
Requires-Dist: casbin-async-sqlalchemy-adapter>=1.0.0; extra == 'casbin'
Requires-Dist: casbin-redis-adapter>=1.0.0; extra == 'casbin'
Provides-Extra: dev
Requires-Dist: black>=23.12.0; extra == 'dev'
Requires-Dist: httpx>=0.25.0; extra == 'dev'
Requires-Dist: mypy>=1.7.0; extra == 'dev'
Requires-Dist: pre-commit>=3.6.0; extra == 'dev'
Requires-Dist: pytest-asyncio>=0.21.0; extra == 'dev'
Requires-Dist: pytest-cov>=4.1.0; extra == 'dev'
Requires-Dist: pytest-mock>=3.12.0; extra == 'dev'
Requires-Dist: pytest>=7.4.0; extra == 'dev'
Requires-Dist: ruff>=0.1.8; extra == 'dev'
Requires-Dist: types-redis>=4.6.0; extra == 'dev'
Provides-Extra: fastapi
Requires-Dist: fastapi>=0.109.0; extra == 'fastapi'
Requires-Dist: starlette>=0.36.0; extra == 'fastapi'
Provides-Extra: logging
Requires-Dist: netrun-logging>=2.0.0; extra == 'logging'
Provides-Extra: oauth
Requires-Dist: authlib>=1.3.0; extra == 'oauth'
Requires-Dist: httpx>=0.26.0; extra == 'oauth'
